cacheme/__init__.py
cacheme/core.py
cacheme/data.py
cacheme/interfaces.py
cacheme/models.py
cacheme/py.typed
cacheme/serializer.py
cacheme/storages/__init__.py
cacheme/storages/base.py
cacheme/storages/local.py
cacheme/storages/mongo.py
cacheme/storages/mysql.py
cacheme/storages/postgres.py
cacheme/storages/redis.py
cacheme/storages/scripts/mongo.js
cacheme/storages/scripts/mysql.sql
cacheme/storages/scripts/postgresql.sql
cacheme/storages/scripts/sqlite.sql
cacheme/storages/sqldb.py
cacheme/storages/sqlite.py
cacheme/utils.py
cacheme-0.3.0.dist-info/LICENSE
cacheme-0.3.0.dist-info/METADATA
cacheme-0.3.0.dist-info/WHEEL
cacheme-0.3.0.dist-info/RECORD
