Metadata-Version: 2.1
Name: cacheme
Version: 0.3.0
Summary: async caching framework
Author: Yiling-J
Author-email: njjyl723@gmail.com
Requires-Python: >=3.7,<4.0
Classifier: Programming Language :: Python :: 3
Classifier: Programming Language :: Python :: 3.7
Classifier: Programming Language :: Python :: 3.8
Classifier: Programming Language :: Python :: 3.9
Classifier: Programming Language :: Python :: 3.10
Classifier: Programming Language :: Python :: 3.11
Provides-Extra: aiomysql
Provides-Extra: asyncpg
Provides-Extra: motor
Provides-Extra: redis
Requires-Dist: aiomysql (>=0.1.1,<0.2.0) ; extra == "aiomysql"
Requires-Dist: asyncpg (>=0.27.0,<0.28.0) ; extra == "asyncpg"
Requires-Dist: cashews (>=5.3.1,<6.0.0)
Requires-Dist: motor (>=3.1.1,<4.0.0) ; extra == "motor"
Requires-Dist: msgpack (>=1.0.4,<2.0.0)
Requires-Dist: pydantic (>=1.10.4,<2.0.0)
Requires-Dist: redis (>=4.4.2,<5.0.0) ; extra == "redis"
Requires-Dist: theine (>=0.3.0,<0.4.0)
Requires-Dist: typing-extensions (>=4.4.0,<5.0.0)
